auth_uuid/__init__.py
auth_uuid/admin.py
auth_uuid/apps.py
auth_uuid/conf.py
auth_uuid/helper_jwt.py
auth_uuid/jwt_helpers.py
auth_uuid/jwt_payload_handler.py
auth_uuid/jwt_response_payload_handler.py
auth_uuid/manager.py
auth_uuid/middleware.py
auth_uuid/models.py
auth_uuid/settings.py
auth_uuid/migrations/0001_initial.py
auth_uuid/migrations/__init__.py
auth_uuid/tests/faker_factory.py
auth_uuid/tests/test_mixin.py
auth_uuid/utils/user_wrapper.py
simple_user-0.9.1.dist-info/DESCRIPTION.rst
simple_user-0.9.1.dist-info/METADATA
simple_user-0.9.1.dist-info/RECORD
simple_user-0.9.1.dist-info/WHEEL
simple_user-0.9.1.dist-info/metadata.json
simple_user-0.9.1.dist-info/top_level.txt
