Metadata-Version: 2.0
Name: simple-user
Version: 0.9.1
Summary: Simple reusable user storing only uuid and manage JWT Token auth_uuidentication in remote
Home-page: https://github.com/exolever/django-simple-user
Author: Tomas Garzon
Author-email: tomasgarzonhervas@gmail.com
License: MIT
Keywords: simple_user
Platform: UNKNOWN
Classifier: Development Status :: 3 - Alpha
Classifier: Framework :: Django :: 1.11
Classifier: Framework :: Django :: 2.0
Classifier: Intended Audience :: Developers
Classifier: License :: OSI Approved :: BSD License
Classifier: Natural Language :: English
Classifier: Programming Language :: Python :: 2
Classifier: Programming Language :: Python :: 2.7
Classifier: Programming Language :: Python :: 3
Classifier: Programming Language :: Python :: 3.4
Classifier: Programming Language :: Python :: 3.5
Classifier: Programming Language :: Python :: 3.6
Requires-Dist: django-model-utils (>=2.0)
